notelate/__init__.py
notelate/scripts/__init__.py
notelate/scripts/app.py
notelate/scripts/notelate.py
notelate/templates/__init__.py
notelate-0.0.5.dist-info/LICENSE
notelate-0.0.5.dist-info/METADATA
notelate-0.0.5.dist-info/WHEEL
notelate-0.0.5.dist-info/entry_points.txt
notelate-0.0.5.dist-info/top_level.txt
notelate-0.0.5.dist-info/RECORD
